europy/__init__.py
europy/notebook.py
europy/utils.py
europy/decorator/__init__.py
europy/decorator/factories.py
europy/lifecycle/__init__.py
europy/lifecycle/markdowner.py
europy/lifecycle/model_card.py
europy/lifecycle/model_details.py
europy/lifecycle/report.py
europy/lifecycle/report_figure.py
europy/lifecycle/reporting.py
europy/lifecycle/result.py
europy/lifecycle/result_promise.py
tests/__init__.py
tests/conftest.py
tests/test_europy.py
EuroPy-1.0.2.dist-info/LICENSE
EuroPy-1.0.2.dist-info/METADATA
EuroPy-1.0.2.dist-info/WHEEL
EuroPy-1.0.2.dist-info/top_level.txt
EuroPy-1.0.2.dist-info/RECORD
