Metadata-Version: 2.1
Name: EuroPy
Version: 1.0.2
Summary: EuroPy testing framework for Machine Learning
Home-page: https://github.com/EuroPy/EuroPyt
Author: Matthew Alvarez, Jenny Lam, Sundar Rajan, Blaine Rothrock
Author-email: author@example.com
License: UNKNOWN
Platform: UNKNOWN
Classifier: Programming Language :: Python :: 3
Classifier: License :: OSI Approved :: Apache Software License
Classifier: Operating System :: OS Independent
Classifier: Framework :: Pytest
Requires-Python: >=3.6
